bukmacherska/__init__.py
bukmacherska/bukmacherska.py
bukmacherska/test_bukmacherska.py
bukmacherska-0.1.3.dist-info/METADATA
bukmacherska-0.1.3.dist-info/WHEEL
bukmacherska-0.1.3.dist-info/top_level.txt
bukmacherska-0.1.3.dist-info/RECORD
