Metadata-Version: 2.2
Name: bukmacherska
Version: 0.1.3
Summary: Opis Twojej biblioteki bukmacherskiej
Home-page: https://github.com/twoj_repo/bukmacherska
Author: Twoje Imię
Author-email: twojemail@example.com
Classifier: Programming Language :: Python :: 3
Classifier: License :: OSI Approved :: MIT License
Classifier: Operating System :: OS Independent
Requires-Python: >=3.6
Requires-Dist: numpy
Requires-Dist: scipy
Requires-Dist: matplotlib
Dynamic: author
Dynamic: author-email
Dynamic: classifier
Dynamic: description
Dynamic: description-content-type
Dynamic: home-page
Dynamic: requires-dist
Dynamic: requires-python
Dynamic: summary
